{
  "date": "2022-12-18",
  "converter": {
    "filename": "converter",
    "display": "OpenSVIP 歌声合成工程文件转换器",
    "downloads": {
      "recent": [
        8,
        12,
        9,
        5,
        17,
        6,
        4,
        7,
        6,
        10
      ],
      "total": 1468
    }
  },
  "plugins": [
    {
      "identifier": "ace",
      "filename": "plugin_ace",
      "display": "ACE Studio 工程文件",
      "downloads": {
        "yesterday": 2,
        "weekly": 12,
        "total": 742
      }
    },
    {
      "identifier": "diffsinger",
      "filename": "plugin_diffsinger",
      "display": "DiffSinger 参数文件",
      "downloads": {
        "yesterday": 4,
        "weekly": 24,
        "total": 56
      }
    },
    {
      "identifier": "gj",
      "filename": "plugin_gjgj",
      "display": "歌叽歌叽工程文件",
      "downloads": {
        "yesterday": 1,
        "weekly": 6,
        "total": 257
      }
    },
    {
      "identifier": "json",
      "filename": "plugin_jsonsvip",
      "display": "OpenSVIP Model 文件",
      "downloads": {
        "yesterday": 2,
        "weekly": 6,
        "total": 233
      }
    },
    {
      "identifier": "lrc",
      "filename": "plugin_lrc",
      "display": "LRC 歌词文件",
      "downloads": {
        "yesterday": 2,
        "weekly": 9,
        "total": 246
      }
    },
    {
      "identifier": "midi",
      "filename": "plugin_midi",
      "display": "MIDI 文件",
      "downloads": {
        "yesterday": 3,
        "weekly": 17,
        "total": 823
      }
    },
    {
      "identifier": "srt",
      "filename": "plugin_srt",
      "display": "SRT 字幕文件",
      "downloads": {
        "yesterday": 2,
        "weekly": 5,
        "total": 147
      }
    },
    {
      "identifier": "svip",
      "filename": "plugin_binsvip",
      "display": "X Studio 工程文件",
      "downloads": {
        "yesterday": 8,
        "weekly": 16,
        "total": 421
      }
    },
    {
      "identifier": "svip3",
      "filename": "plugin_svip3",
      "display": "X Studio 3 工程文件",
      "downloads": {
        "yesterday": 4,
        "weekly": 17,
        "total": 145
      }
    },
    {
      "identifier": "svp",
      "filename": "plugin_synthv",
      "display": "Synthesizer V 工程文件",
      "downloads": {
        "yesterday": 3,
        "weekly": 18,
        "total": 666
      }
    },
    {
      "identifier": "ustx",
      "filename": "plugin_ustx",
      "display": "OpenUTAU 工程文件",
      "downloads": {
        "yesterday": 4,
        "weekly": 10,
        "total": 246
      }
    },
    {
      "identifier": "vog",
      "filename": "plugin_vogen",
      "display": "Project Vogen 工程文件",
      "downloads": {
        "yesterday": 1,
        "weekly": 6,
        "total": 161
      }
    },
    {
      "identifier": "y77",
      "filename": "plugin_y77",
      "display": "元七七工程文件",
      "downloads": {
        "yesterday": 2,
        "weekly": 6,
        "total": 133
      }
    }
  ]
}