{
  "date": "2023-07-23",
  "converter": {
    "filename": "converter",
    "display": "OpenSVIP 歌声合成工程文件转换器",
    "downloads": {
      "recent": [
        4,
        7,
        6,
        10,
        5,
        14,
        3,
        4,
        10,
        9
      ],
      "total": 4324
    }
  },
  "plugins": [
    {
      "identifier": "ace",
      "filename": "plugin_ace",
      "display": "ACE Studio 工程文件",
      "downloads": {
        "yesterday": 2,
        "weekly": 0,
        "total": 1248
      }
    },
    {
      "identifier": "diffsinger",
      "filename": "plugin_diffsinger",
      "display": "DiffSinger 参数文件",
      "downloads": {
        "yesterday": 1,
        "weekly": 10,
        "total": 1198
      }
    },
    {
      "identifier": "gj",
      "filename": "plugin_gjgj",
      "display": "歌叽歌叽工程文件",
      "downloads": {
        "yesterday": 0,
        "weekly": 2,
        "total": 614
      }
    },
    {
      "identifier": "json",
      "filename": "plugin_jsonsvip",
      "display": "OpenSVIP Model 文件",
      "downloads": {
        "yesterday": 1,
        "weekly": 4,
        "total": 637
      }
    },
    {
      "identifier": "lrc",
      "filename": "plugin_lrc",
      "display": "LRC 歌词文件",
      "downloads": {
        "yesterday": 1,
        "weekly": 1,
        "total": 672
      }
    },
    {
      "identifier": "midi",
      "filename": "plugin_midi",
      "display": "MIDI 文件",
      "downloads": {
        "yesterday": 2,
        "weekly": 22,
        "total": 1967
      }
    },
    {
      "identifier": "srt",
      "filename": "plugin_srt",
      "display": "SRT 字幕文件",
      "downloads": {
        "yesterday": 1,
        "weekly": 1,
        "total": 447
      }
    },
    {
      "identifier": "svg",
      "filename": "plugin_svg",
      "display": "可缩放矢量图形",
      "downloads": {
        "yesterday": 1,
        "weekly": 3,
        "total": 155
      }
    },
    {
      "identifier": "svip",
      "filename": "plugin_binsvip",
      "display": "X Studio 工程文件",
      "downloads": {
        "yesterday": 3,
        "weekly": 9,
        "total": 1201
      }
    },
    {
      "identifier": "svip3",
      "filename": "plugin_svip3",
      "display": "X Studio 3 工程文件",
      "downloads": {
        "yesterday": 6,
        "weekly": 9,
        "total": 691
      }
    },
    {
      "identifier": "svp",
      "filename": "plugin_synthv",
      "display": "Synthesizer V 工程文件",
      "downloads": {
        "yesterday": 1,
        "weekly": 11,
        "total": 1622
      }
    },
    {
      "identifier": "ustx",
      "filename": "plugin_ustx",
      "display": "OpenUTAU 工程文件",
      "downloads": {
        "yesterday": 1,
        "weekly": 13,
        "total": 916
      }
    },
    {
      "identifier": "vog",
      "filename": "plugin_vogen",
      "display": "Project Vogen 工程文件",
      "downloads": {
        "yesterday": 0,
        "weekly": 1,
        "total": 406
      }
    },
    {
      "identifier": "y77",
      "filename": "plugin_y77",
      "display": "元七七工程文件",
      "downloads": {
        "yesterday": 0,
        "weekly": 1,
        "total": 379
      }
    }
  ]
}